cartesia_mcp/__init__.py
cartesia_mcp/server.py
cartesia_mcp/utils.py
cartesia_mcp/custom_types/__init__.py
cartesia_mcp/custom_types/tool_results.py
cartesia_mcp/custom_types/tool_type.py
cartesia_mcp-0.1.6.dist-info/METADATA
cartesia_mcp-0.1.6.dist-info/WHEEL
cartesia_mcp-0.1.6.dist-info/entry_points.txt
cartesia_mcp-0.1.6.dist-info/top_level.txt
cartesia_mcp-0.1.6.dist-info/RECORD
